{
  "anime_id": "202601_kiyou_bimbou_c1",
  "title": "勇者パーティを追い出された器用貧乏",
  "official_url": "https://kiyou-bimbou.com/]]",
  "hashtag": null,
  "station_master": null,
  "cast": [],
  "staff": {},
  "sources": {
    "manga_amazon": null,
    "goods": []
  },
  "syoboi_tid": 7655,
  "mal_id": 61128,
  "image_url": "https://myanimelist.net/images/anime/1486/153135l.webp",
  "genres": [
    "Action",
    "Adventure",
    "Fantasy"
  ],
  "themes": [],
  "score": 6.64,
  "studio": "animation studio42",
  "title_english": "Jack-of-All-Trades, Party of None",
  "title_japanese": "勇者パーティを追い出された器用貧乏"
}