{
  "anime_id": "202601_yamishibai_tx_c1",
  "title": "闇芝居 十六期",
  "official_url": "https://www.tv-tokyo.co.jp/anime/yamishibai16/]]",
  "hashtag": null,
  "station_master": null,
  "cast": [],
  "staff": {},
  "sources": {
    "manga_amazon": null,
    "goods": []
  },
  "syoboi_tid": 7715,
  "mal_id": 63087,
  "image_url": "https://myanimelist.net/images/anime/1666/154215l.webp",
  "genres": [
    "Avant Garde",
    "Horror",
    "Supernatural"
  ],
  "themes": [],
  "score": 5.85,
  "studio": "ILCA",
  "title_english": "Theatre of Darkness: Yamishibai 16",
  "title_japanese": "闇芝居 十六期"
}