{
  "anime_id": "202601_jujutsushimetsu_c1",
  "title": "呪術廻戦 死滅回游 前編",
  "official_url": "https://jujutsukaisen.jp/",
  "hashtag": null,
  "station_master": "MBS",
  "cast": [],
  "staff": {},
  "sources": {
    "manga_amazon": null,
    "goods": []
  },
  "mal_id": 57658,
  "image_url": "https://myanimelist.net/images/anime/1659/154920l.webp",
  "genres": [
    "Action",
    "Supernatural"
  ],
  "themes": [],
  "score": 8.58,
  "studio": "MAPPA",
  "title_english": "Jujutsu Kaisen: The Culling Game Part 1",
  "title_japanese": "呪術廻戦 「死滅回游 前編」"
}